{
  "tables": [
    {
      "id": 1,
      "table": "maya",
      "columns": [
        {
          "name": "date",
          "label": "日期",
          "type": "date"
        },
        {
          "name": "name",
          "label": "姓名",
          "type": "text"
        },
        {
          "name": "score",
          "label": "分數",
          "type": "number"
        },
        {
          "name": "temple",
          "label": "神廟",
          "type": "number"
        }
      ]
    },

    {
      "id": 2,
      "table": "test",
      "columns": [
        {
          "name": "name",
          "label": "類別",
          "type": "text"
        },
        {
          "name": "prior",
          "label": "順序",
          "type": "number"
        }
      ]
    },

    {
      "id": 3,
      "table": "balances",
      "columns": [
        {
          "name": "date",
          "label": "日期",
          "type": "date"
        },
        {
          "name": "cate",
          "label": "類別",
          "type": "text"
        },
        {
          "name": "title",
          "label": "項目",
          "type": "text"
        },
        {
          "name": "expense",
          "label": "支出",
          "type": "number"
        }
      ]
    },

    {
      "id": 4,
      "table": "cates",
      "columns": [
        {
          "name": "name",
          "label": "類別",
          "type": "text"
        },
        {
          "name": "prior",
          "label": "順序",
          "type": "number"
        }
      ]
    },
    {
      "id": 5,
      "table": "stockStat",
      "columns": [
        {
          "name": "stockId",
          "label": "代號",
          "type": "text"
        },
        {
          "name": "name",
          "label": "名稱",
          "type": "text"
        },
      

        {
          "name": "price",
          "label": "價格",
          "type": "number"
        },

        {
          "name": "qtys",
          "label": "股數",
          "type": "number"
        }
      ]
    },
    {
      "id": 6,
      "table": "stockTransaction",
      "columns": [
        {
          "name": "date",
          "label": "日期",
          "type": "date"
        },

        {
          "name": "name",
          "label": "名稱",
          "type": "text"
        },
        {
          "name": "qty",
          "label": "股數",
          "type": "number"
        },
        {
          "name": "cost",
          "label": "金額",
          "type": "number"
        }
      ]
    }
  ]
}
